<?xml version="1.0" encoding="utf-8" ?>
<!-- Copyright 2023 Xtendoo - Jaime Millán
     License AGPL-3.0 or later (https://www.gnu.org/licenses/agpl). -->
<odoo>
    <data>
        <record id="view_sale_order_form_custom" model="ir.ui.view">
            <field name="name">sale.order.form.custom</field>
            <field name="model">sale.order</field>
            <field name="inherit_id" ref="sale.view_order_form"/>
            <field name="arch" type="xml">
                <xpath expr="//page[@name='order_lines']/field[@name='order_line']/tree/field[@name='name']"
                       position="before">
                    <field name="student_id"/>
                </xpath>
                <xpath expr="//page[@name='order_lines']/field[@name='order_line']/tree/field[@name='price_unit']"
                       position="attributes">
                    <attribute name="string">€/Horas</attribute>
                </xpath>
                <xpath expr="//page[@name='order_lines']/field[@name='order_line']/tree/field[@name='product_uom_qty']"
                       position="attributes">
                    <attribute name="string">Horas</attribute>
                </xpath>
            </field>
        </record>
    </data>
</odoo>
